agents/python/observee_agents/__init__.py
agents/python/observee_agents/agents/agent.py
agents/python/observee_agents/providers/__init__.py
agents/python/observee_agents/providers/anthropic_provider.py
agents/python/observee_agents/providers/base.py
agents/python/observee_agents/providers/gemini_provider.py
agents/python/observee_agents/providers/openai_provider.py
agents/python/observee_agents/search/__init__.py
agents/python/observee_agents/search/base.py
agents/python/observee_agents/search/bm25_filter.py
agents/python/observee_agents/search/cloud_filter.py
agents/python/observee_agents/search/cloud_infrastructure.py
agents/python/observee_agents/search/local_embedding_filter.py
agents/python/observee_agents/utils/__init__.py
agents/python/observee_agents/utils/langchain_converter.py
agents/python/observee_agents/utils/mcp_client.py
auth/python/auth-mcp/__init__.py
auth/python/auth-mcp/mcpauth.py
logger/python/mcp-logger/__init__.py
logger/python/mcp-logger/configuration.py
logger/python/mcp-logger/constants.py
logger/python/mcp-logger/logging.py
logger/python/mcp-logger/models.py
logger/python/mcp-logger/utils.py
observee-0.1.20.dist-info/licenses/LICENCE
observee-0.1.20.dist-info/METADATA
observee-0.1.20.dist-info/WHEEL
observee-0.1.20.dist-info/top_level.txt
observee-0.1.20.dist-info/RECORD
