Metadata-Version: 2.4
Name: observee
Version: 0.1.20
Summary: Observee SDK - Tool usage logging, monitoring, authentication, and agent system for LLM integrations
Author-email: Observee Team <contact@observee.ai>
Maintainer-email: Observee Team <contact@observee.ai>
License: MIT
Project-URL: Homepage, https://observee.ai
Project-URL: Documentation, https://docs.observee.ai
Project-URL: Repository, https://github.com/observee-ai/observee
Project-URL: Bug Reports, https://github.com/observee-ai/observee/issues
Keywords: mcp,agent,llm,anthropic,openai,gemini,tools,logging,monitoring,oauth,authentication
Classifier: Development Status :: 4 - Beta
Classifier: Intended Audience :: Developers
Classifier: License :: OSI Approved :: MIT License
Classifier: Operating System :: OS Independent
Classifier: Programming Language :: Python :: 3
Classifier: Programming Language :: Python :: 3.8
Classifier: Programming Language :: Python :: 3.9
Classifier: Programming Language :: Python :: 3.10
Classifier: Programming Language :: Python :: 3.11
Classifier: Programming Language :: Python :: 3.12
Classifier: Topic :: Software Development :: Libraries :: Python Modules
Classifier: Topic :: Scientific/Engineering :: Artificial Intelligence
Classifier: Topic :: System :: Logging
Classifier: Topic :: Internet :: WWW/HTTP
Requires-Python: >=3.8
License-File: LICENCE
Requires-Dist: httpx
Requires-Dist: pydantic
Requires-Dist: requests>=2.25.0
Requires-Dist: python-dotenv>=0.19.0
Requires-Dist: fastmcp
Requires-Dist: anthropic
Requires-Dist: google-genai
Requires-Dist: openai
Requires-Dist: rich
Requires-Dist: bm25s
Requires-Dist: langchain
Requires-Dist: langchain-core
Requires-Dist: langchain-openai
Requires-Dist: langchain-anthropic
Requires-Dist: langchain-google-genai
Requires-Dist: jsonschema-pydantic
Requires-Dist: groq
Provides-Extra: dev
Requires-Dist: pytest>=7.0; extra == "dev"
Requires-Dist: pytest-asyncio>=0.18.0; extra == "dev"
Requires-Dist: pytest-cov>=3.0; extra == "dev"
Requires-Dist: black>=22.0; extra == "dev"
Requires-Dist: flake8>=4.0; extra == "dev"
Requires-Dist: mypy>=0.950; extra == "dev"
Requires-Dist: types-requests; extra == "dev"
Requires-Dist: build; extra == "dev"
Requires-Dist: twine; extra == "dev"
Provides-Extra: embedding
Requires-Dist: fastembed>=0.1.0; extra == "embedding"
Requires-Dist: sentence-transformers; extra == "embedding"
Provides-Extra: cloud
Requires-Dist: pinecone-client>=2.0.0; extra == "cloud"
Requires-Dist: pinecone; extra == "cloud"
Dynamic: license-file
